replay/__init__.py
replay/data/__init__.py
replay/data/dataset.py
replay/data/dataset_utils/__init__.py
replay/data/dataset_utils/dataset_label_encoder.py
replay/data/nn/__init__.py
replay/data/nn/parquet/__init__.py
replay/data/nn/parquet/collate.py
replay/data/nn/parquet/constants/__init__.py
replay/data/nn/parquet/constants/batches.py
replay/data/nn/parquet/constants/device.py
replay/data/nn/parquet/constants/filesystem.py
replay/data/nn/parquet/constants/metadata.py
replay/data/nn/parquet/fixed_batch_dataset.py
replay/data/nn/parquet/impl/__init__.py
replay/data/nn/parquet/impl/array_1d_column.py
replay/data/nn/parquet/impl/array_2d_column.py
replay/data/nn/parquet/impl/column_protocol.py
replay/data/nn/parquet/impl/indexing.py
replay/data/nn/parquet/impl/masking.py
replay/data/nn/parquet/impl/named_columns.py
replay/data/nn/parquet/impl/numeric_column.py
replay/data/nn/parquet/impl/utils.py
replay/data/nn/parquet/info/__init__.py
replay/data/nn/parquet/info/distributed_info.py
replay/data/nn/parquet/info/partitioning.py
replay/data/nn/parquet/info/replicas.py
replay/data/nn/parquet/info/worker_info.py
replay/data/nn/parquet/iterable_dataset.py
replay/data/nn/parquet/iterator.py
replay/data/nn/parquet/metadata/__init__.py
replay/data/nn/parquet/metadata/metadata.py
replay/data/nn/parquet/parquet_dataset.py
replay/data/nn/parquet/parquet_module.py
replay/data/nn/parquet/partitioned_iterable_dataset.py
replay/data/nn/parquet/utils/__init__.py
replay/data/nn/parquet/utils/compute_length.py
replay/data/nn/schema.py
replay/data/nn/sequence_tokenizer.py
replay/data/nn/sequential_dataset.py
replay/data/nn/torch_sequential_dataset.py
replay/data/nn/utils.py
replay/data/schema.py
replay/data/spark_schema.py
replay/data/utils/__init__.py
replay/data/utils/batching.py
replay/data/utils/typing/__init__.py
replay/data/utils/typing/dtype.py
replay/metrics/__init__.py
replay/metrics/base_metric.py
replay/metrics/categorical_diversity.py
replay/metrics/coverage.py
replay_rec-0.21.0.dist-info/METADATA
replay_rec-0.21.0.dist-info/WHEEL
replay_rec-0.21.0.dist-info/licenses/LICENSE
replay_rec-0.21.0.dist-info/licenses/NOTICE
replay_rec-0.21.0.dist-info/RECORD
