Metadata-Version: 2.4
Name: replay-rec
Version: 0.21.0
Summary: RecSys Library
License-Expression: Apache-2.0
License-File: LICENSE
License-File: NOTICE
Author: AI Lab
Requires-Python: >=3.9, <3.13
Classifier: Operating System :: Unix
Classifier: Development Status :: 4 - Beta
Classifier: Environment :: Console
Classifier: Intended Audience :: Developers
Classifier: Intended Audience :: Science/Research
Classifier: Natural Language :: English
Classifier: Topic :: Scientific/Engineering :: Artificial Intelligence
Provides-Extra: spark
Provides-Extra: torch
Provides-Extra: torch-cpu
Requires-Dist: lightning (<2.6.0) ; extra == "torch" or extra == "torch-cpu"
Requires-Dist: lightning ; extra == "torch"
Requires-Dist: lightning ; extra == "torch-cpu"
Requires-Dist: numpy (>=1.20.0,<2)
Requires-Dist: pandas (>=1.3.5,<2.4.0)
Requires-Dist: polars (<2.0)
Requires-Dist: psutil (<=7.0.0) ; extra == "spark"
Requires-Dist: psutil ; extra == "spark"
Requires-Dist: pyarrow (<22.0)
Requires-Dist: pyspark (>=3.0,<3.5) ; extra == "spark"
Requires-Dist: pyspark ; extra == "spark"
Requires-Dist: pytorch-optimizer (>=3.8.0,<3.9.0) ; extra == "torch" or extra == "torch-cpu"
Requires-Dist: pytorch-optimizer ; extra == "torch"
Requires-Dist: pytorch-optimizer ; extra == "torch-cpu"
Requires-Dist: scikit-learn (>=1.6.1,<1.7.0)
Requires-Dist: scipy (>=1.8.1,<2.0.0)
Requires-Dist: setuptools
Requires-Dist: torch (>=1.8,<3.0.0) ; extra == "torch" or extra == "torch-cpu"
Requires-Dist: torch ; extra == "torch"
Requires-Dist: torch ; extra == "torch-cpu"
Requires-Dist: tqdm (>=4.67,<5)
Project-URL: Homepage, https://sb-ai-lab.github.io/RePlay/
Project-URL: Repository, https://github.com/sb-ai-lab/RePlay
